LICENSE.txt
MANIFEST.in
README.rst
setup.py
mezzanine_faq/__init__.py
mezzanine_faq/__init__.pyc
mezzanine_faq/admin.py
mezzanine_faq/admin.pyc
mezzanine_faq/models.py
mezzanine_faq/models.pyc
mezzanine_faq/tests.py
mezzanine_faq/views.py
mezzanine_faq.egg-info/PKG-INFO
mezzanine_faq.egg-info/SOURCES.txt
mezzanine_faq.egg-info/dependency_links.txt
mezzanine_faq.egg-info/top_level.txt
mezzanine_faq/.ropeproject/config.py
mezzanine_faq/.ropeproject/globalnames
mezzanine_faq/.ropeproject/history
mezzanine_faq/.ropeproject/objectdb
mezzanine_faq/locale/cs/LC_MESSAGES/django.mo
mezzanine_faq/locale/cs/LC_MESSAGES/django.po
mezzanine_faq/migrations/0001_initial.py
mezzanine_faq/migrations/0001_initial.pyc
mezzanine_faq/migrations/__init__.py
mezzanine_faq/migrations/__init__.pyc
mezzanine_faq/templates/includes/faqlist.html
mezzanine_faq/templates/pages/faq.html
mezzanine_faq/templatetags/__init__.py
mezzanine_faq/templatetags/__init__.pyc
mezzanine_faq/templatetags/faq_tags.py
mezzanine_faq/templatetags/faq_tags.pyc
mezzanine_faq/templatetags/references_tags.pyc
mezzanine_faq/templatetags/.ropeproject/config.py
mezzanine_faq/templatetags/.ropeproject/globalnames
mezzanine_faq/templatetags/.ropeproject/history
mezzanine_faq/templatetags/.ropeproject/objectdb