Metadata-Version: 1.1
Name: mezzanine-faq
Version: 0.1
Summary: 
